bedrock_world_operator-1.5.0.dist-info/licenses/LICENSE
bedrockworldoperator/__init__.py
bedrockworldoperator/dynamic_libs/bedrock-world-operator_android_arm64.so
bedrockworldoperator/dynamic_libs/bedrock-world-operator_linux_amd64.so
bedrockworldoperator/dynamic_libs/bedrock-world-operator_linux_arm64.so
bedrockworldoperator/dynamic_libs/bedrock-world-operator_macos_amd64.dylib
bedrockworldoperator/dynamic_libs/bedrock-world-operator_macos_arm64.dylib
bedrockworldoperator/dynamic_libs/bedrock-world-operator_windows_amd64.dll
bedrockworldoperator/dynamic_libs/bedrock-world-operator_windows_x86.dll
bedrockworldoperator/internal/__init__.py
bedrockworldoperator/internal/load_dynamic_library.py
bedrockworldoperator/internal/symbol_export_chunk.py
bedrockworldoperator/internal/symbol_export_conversion.py
bedrockworldoperator/internal/symbol_export_sub_chunk.py
bedrockworldoperator/internal/symbol_export_world.py
bedrockworldoperator/internal/symbol_export_world_underlying.py
bedrockworldoperator/internal/types.py
bedrockworldoperator/utils/__init__.py
bedrockworldoperator/utils/getByte.py
bedrockworldoperator/utils/getString.py
bedrockworldoperator/utils/marshalNBT.py
bedrockworldoperator/utils/unmarshalNBT.py
bedrockworldoperator/world/__init__.py
bedrockworldoperator/world/chunk.py
bedrockworldoperator/world/constant.py
bedrockworldoperator/world/conversion.py
bedrockworldoperator/world/define.py
bedrockworldoperator/world/level_dat.py
bedrockworldoperator/world/sub_chunk.py
bedrockworldoperator/world/world.py
bedrock_world_operator-1.5.0.dist-info/METADATA
bedrock_world_operator-1.5.0.dist-info/WHEEL
bedrock_world_operator-1.5.0.dist-info/top_level.txt
bedrock_world_operator-1.5.0.dist-info/RECORD
