Metadata-Version: 2.4
Name: bedrock-world-operator
Version: 1.5.0
Summary: An operator based on Go that aims to provide interface for Python that could operating NetEase/Standard Minecraft bedrock game saves.
Home-page: https://github.com/TriM-Organization/bedrock-world-operator
Author: Minecraft Muti-Media Organization
Author-email: TriM-Organization@hotmail.com
Classifier: License :: OSI Approved :: MIT License
Classifier: Programming Language :: Python :: 3
Classifier: Programming Language :: Go
Classifier: Operating System :: POSIX :: Linux
Classifier: Operating System :: Microsoft :: Windows
Classifier: Operating System :: MacOS
Requires-Python: >=3.10
License-File: LICENSE
Requires-Dist: nbtlib>=2.0.4
Requires-Dist: numpy
Dynamic: author
Dynamic: author-email
Dynamic: classifier
Dynamic: description
Dynamic: description-content-type
Dynamic: home-page
Dynamic: license-file
Dynamic: requires-dist
Dynamic: requires-python
Dynamic: summary
